[
  {
    "id": "in-glossary-001",
    "term": "信息素养",
    "definition": "信息素养说明",
    "category": "InfoLit",
    "tags": [
      "InfoLit"
    ],
    "updatedAt": "2026-07-03T00:00:00.000Z"
  },
  {
    "id": "in-glossary-002",
    "term": "信息检索",
    "definition": "信息检索说明",
    "category": "InfoLit",
    "tags": [
      "InfoLit"
    ],
    "updatedAt": "2026-07-03T00:00:00.000Z"
  },
  {
    "id": "in-glossary-003",
    "term": "布尔运算",
    "definition": "布尔运算说明",
    "category": "InfoLit",
    "tags": [
      "InfoLit"
    ],
    "updatedAt": "2026-07-03T00:00:00.000Z"
  },
  {
    "id": "in-glossary-004",
    "term": "可信度",
    "definition": "可信度说明",
    "category": "InfoLit",
    "tags": [
      "InfoLit"
    ],
    "updatedAt": "2026-07-03T00:00:00.000Z"
  },
  {
    "id": "in-glossary-005",
    "term": "事实核查",
    "definition": "事实核查说明",
    "category": "InfoLit",
    "tags": [
      "InfoLit"
    ],
    "updatedAt": "2026-07-03T00:00:00.000Z"
  },
  {
    "id": "in-glossary-006",
    "term": "学术搜索",
    "definition": "学术搜索说明",
    "category": "InfoLit",
    "tags": [
      "InfoLit"
    ],
    "updatedAt": "2026-07-03T00:00:00.000Z"
  },
  {
    "id": "in-glossary-007",
    "term": "论文阅读",
    "definition": "论文阅读说明",
    "category": "InfoLit",
    "tags": [
      "InfoLit"
    ],
    "updatedAt": "2026-07-03T00:00:00.000Z"
  },
  {
    "id": "in-glossary-008",
    "term": "引用规范",
    "definition": "引用规范说明",
    "category": "InfoLit",
    "tags": [
      "InfoLit"
    ],
    "updatedAt": "2026-07-03T00:00:00.000Z"
  },
  {
    "id": "in-glossary-009",
    "term": "知识库",
    "definition": "知识库说明",
    "category": "InfoLit",
    "tags": [
      "InfoLit"
    ],
    "updatedAt": "2026-07-03T00:00:00.000Z"
  },
  {
    "id": "in-glossary-010",
    "term": "版权",
    "definition": "版权说明",
    "category": "InfoLit",
    "tags": [
      "InfoLit"
    ],
    "updatedAt": "2026-07-03T00:00:00.000Z"
  },
  {
    "id": "in-glossary-011",
    "term": "关键词",
    "definition": "关键词说明",
    "category": "InfoLit",
    "tags": [
      "InfoLit"
    ],
    "updatedAt": "2026-07-03T00:00:00.000Z"
  },
  {
    "id": "in-glossary-012",
    "term": "高级搜索",
    "definition": "高级搜索说明",
    "category": "InfoLit",
    "tags": [
      "InfoLit"
    ],
    "updatedAt": "2026-07-03T00:00:00.000Z"
  },
  {
    "id": "in-glossary-013",
    "term": "文献管理",
    "definition": "文献管理说明",
    "category": "InfoLit",
    "tags": [
      "InfoLit"
    ],
    "updatedAt": "2026-07-03T00:00:00.000Z"
  },
  {
    "id": "in-glossary-014",
    "term": "研究报告",
    "definition": "研究报告说明",
    "category": "InfoLit",
    "tags": [
      "InfoLit"
    ],
    "updatedAt": "2026-07-03T00:00:00.000Z"
  },
  {
    "id": "in-glossary-015",
    "term": "信息源",
    "definition": "信息源说明",
    "category": "InfoLit",
    "tags": [
      "InfoLit"
    ],
    "updatedAt": "2026-07-03T00:00:00.000Z"
  },
  {
    "id": "in-glossary-016",
    "term": "IL概念15",
    "definition": "IL概念15说明",
    "category": "InfoLit",
    "tags": [
      "InfoLit"
    ],
    "updatedAt": "2026-07-03T00:00:00.000Z"
  },
  {
    "id": "in-glossary-017",
    "term": "IL概念16",
    "definition": "IL概念16说明",
    "category": "InfoLit",
    "tags": [
      "InfoLit"
    ],
    "updatedAt": "2026-07-03T00:00:00.000Z"
  },
  {
    "id": "in-glossary-018",
    "term": "IL概念17",
    "definition": "IL概念17说明",
    "category": "InfoLit",
    "tags": [
      "InfoLit"
    ],
    "updatedAt": "2026-07-03T00:00:00.000Z"
  },
  {
    "id": "in-glossary-019",
    "term": "IL概念18",
    "definition": "IL概念18说明",
    "category": "InfoLit",
    "tags": [
      "InfoLit"
    ],
    "updatedAt": "2026-07-03T00:00:00.000Z"
  },
  {
    "id": "in-glossary-020",
    "term": "IL概念19",
    "definition": "IL概念19说明",
    "category": "InfoLit",
    "tags": [
      "InfoLit"
    ],
    "updatedAt": "2026-07-03T00:00:00.000Z"
  },
  {
    "id": "in-glossary-021",
    "term": "IL概念20",
    "definition": "IL概念20说明",
    "category": "InfoLit",
    "tags": [
      "InfoLit"
    ],
    "updatedAt": "2026-07-03T00:00:00.000Z"
  },
  {
    "id": "in-glossary-022",
    "term": "IL概念21",
    "definition": "IL概念21说明",
    "category": "InfoLit",
    "tags": [
      "InfoLit"
    ],
    "updatedAt": "2026-07-03T00:00:00.000Z"
  },
  {
    "id": "in-glossary-023",
    "term": "IL概念22",
    "definition": "IL概念22说明",
    "category": "InfoLit",
    "tags": [
      "InfoLit"
    ],
    "updatedAt": "2026-07-03T00:00:00.000Z"
  },
  {
    "id": "in-glossary-024",
    "term": "IL概念23",
    "definition": "IL概念23说明",
    "category": "InfoLit",
    "tags": [
      "InfoLit"
    ],
    "updatedAt": "2026-07-03T00:00:00.000Z"
  },
  {
    "id": "in-glossary-025",
    "term": "IL概念24",
    "definition": "IL概念24说明",
    "category": "InfoLit",
    "tags": [
      "InfoLit"
    ],
    "updatedAt": "2026-07-03T00:00:00.000Z"
  },
  {
    "id": "in-glossary-026",
    "term": "IL概念25",
    "definition": "IL概念25说明",
    "category": "InfoLit",
    "tags": [
      "InfoLit"
    ],
    "updatedAt": "2026-07-03T00:00:00.000Z"
  },
  {
    "id": "in-glossary-027",
    "term": "IL概念26",
    "definition": "IL概念26说明",
    "category": "InfoLit",
    "tags": [
      "InfoLit"
    ],
    "updatedAt": "2026-07-03T00:00:00.000Z"
  },
  {
    "id": "in-glossary-028",
    "term": "IL概念27",
    "definition": "IL概念27说明",
    "category": "InfoLit",
    "tags": [
      "InfoLit"
    ],
    "updatedAt": "2026-07-03T00:00:00.000Z"
  },
  {
    "id": "in-glossary-029",
    "term": "IL概念28",
    "definition": "IL概念28说明",
    "category": "InfoLit",
    "tags": [
      "InfoLit"
    ],
    "updatedAt": "2026-07-03T00:00:00.000Z"
  },
  {
    "id": "in-glossary-030",
    "term": "IL概念29",
    "definition": "IL概念29说明",
    "category": "InfoLit",
    "tags": [
      "InfoLit"
    ],
    "updatedAt": "2026-07-03T00:00:00.000Z"
  },
  {
    "id": "in-glossary-031",
    "term": "IL概念30",
    "definition": "IL概念30说明",
    "category": "InfoLit",
    "tags": [
      "InfoLit"
    ],
    "updatedAt": "2026-07-03T00:00:00.000Z"
  },
  {
    "id": "in-glossary-032",
    "term": "IL概念31",
    "definition": "IL概念31说明",
    "category": "InfoLit",
    "tags": [
      "InfoLit"
    ],
    "updatedAt": "2026-07-03T00:00:00.000Z"
  },
  {
    "id": "in-glossary-033",
    "term": "IL概念32",
    "definition": "IL概念32说明",
    "category": "InfoLit",
    "tags": [
      "InfoLit"
    ],
    "updatedAt": "2026-07-03T00:00:00.000Z"
  },
  {
    "id": "in-glossary-034",
    "term": "IL概念33",
    "definition": "IL概念33说明",
    "category": "InfoLit",
    "tags": [
      "InfoLit"
    ],
    "updatedAt": "2026-07-03T00:00:00.000Z"
  },
  {
    "id": "in-glossary-035",
    "term": "IL概念34",
    "definition": "IL概念34说明",
    "category": "InfoLit",
    "tags": [
      "InfoLit"
    ],
    "updatedAt": "2026-07-03T00:00:00.000Z"
  },
  {
    "id": "in-glossary-036",
    "term": "IL概念35",
    "definition": "IL概念35说明",
    "category": "InfoLit",
    "tags": [
      "InfoLit"
    ],
    "updatedAt": "2026-07-03T00:00:00.000Z"
  },
  {
    "id": "in-glossary-037",
    "term": "IL概念36",
    "definition": "IL概念36说明",
    "category": "InfoLit",
    "tags": [
      "InfoLit"
    ],
    "updatedAt": "2026-07-03T00:00:00.000Z"
  },
  {
    "id": "in-glossary-038",
    "term": "IL概念37",
    "definition": "IL概念37说明",
    "category": "InfoLit",
    "tags": [
      "InfoLit"
    ],
    "updatedAt": "2026-07-03T00:00:00.000Z"
  },
  {
    "id": "in-glossary-039",
    "term": "IL概念38",
    "definition": "IL概念38说明",
    "category": "InfoLit",
    "tags": [
      "InfoLit"
    ],
    "updatedAt": "2026-07-03T00:00:00.000Z"
  },
  {
    "id": "in-glossary-040",
    "term": "IL概念39",
    "definition": "IL概念39说明",
    "category": "InfoLit",
    "tags": [
      "InfoLit"
    ],
    "updatedAt": "2026-07-03T00:00:00.000Z"
  },
  {
    "id": "in-glossary-041",
    "term": "IL概念40",
    "definition": "IL概念40说明",
    "category": "InfoLit",
    "tags": [
      "InfoLit"
    ],
    "updatedAt": "2026-07-03T00:00:00.000Z"
  },
  {
    "id": "in-glossary-042",
    "term": "IL概念41",
    "definition": "IL概念41说明",
    "category": "InfoLit",
    "tags": [
      "InfoLit"
    ],
    "updatedAt": "2026-07-03T00:00:00.000Z"
  },
  {
    "id": "in-glossary-043",
    "term": "IL概念42",
    "definition": "IL概念42说明",
    "category": "InfoLit",
    "tags": [
      "InfoLit"
    ],
    "updatedAt": "2026-07-03T00:00:00.000Z"
  },
  {
    "id": "in-glossary-044",
    "term": "IL概念43",
    "definition": "IL概念43说明",
    "category": "InfoLit",
    "tags": [
      "InfoLit"
    ],
    "updatedAt": "2026-07-03T00:00:00.000Z"
  },
  {
    "id": "in-glossary-045",
    "term": "IL概念44",
    "definition": "IL概念44说明",
    "category": "InfoLit",
    "tags": [
      "InfoLit"
    ],
    "updatedAt": "2026-07-03T00:00:00.000Z"
  },
  {
    "id": "in-glossary-046",
    "term": "IL概念45",
    "definition": "IL概念45说明",
    "category": "InfoLit",
    "tags": [
      "InfoLit"
    ],
    "updatedAt": "2026-07-03T00:00:00.000Z"
  },
  {
    "id": "in-glossary-047",
    "term": "IL概念46",
    "definition": "IL概念46说明",
    "category": "InfoLit",
    "tags": [
      "InfoLit"
    ],
    "updatedAt": "2026-07-03T00:00:00.000Z"
  },
  {
    "id": "in-glossary-048",
    "term": "IL概念47",
    "definition": "IL概念47说明",
    "category": "InfoLit",
    "tags": [
      "InfoLit"
    ],
    "updatedAt": "2026-07-03T00:00:00.000Z"
  },
  {
    "id": "in-glossary-049",
    "term": "IL概念48",
    "definition": "IL概念48说明",
    "category": "InfoLit",
    "tags": [
      "InfoLit"
    ],
    "updatedAt": "2026-07-03T00:00:00.000Z"
  },
  {
    "id": "in-glossary-050",
    "term": "IL概念49",
    "definition": "IL概念49说明",
    "category": "InfoLit",
    "tags": [
      "InfoLit"
    ],
    "updatedAt": "2026-07-03T00:00:00.000Z"
  },
  {
    "id": "in-glossary-051",
    "term": "IL概念50",
    "definition": "IL概念50说明",
    "category": "InfoLit",
    "tags": [
      "InfoLit"
    ],
    "updatedAt": "2026-07-03T00:00:00.000Z"
  },
  {
    "id": "in-glossary-052",
    "term": "IL概念51",
    "definition": "IL概念51说明",
    "category": "InfoLit",
    "tags": [
      "InfoLit"
    ],
    "updatedAt": "2026-07-03T00:00:00.000Z"
  },
  {
    "id": "in-glossary-053",
    "term": "IL概念52",
    "definition": "IL概念52说明",
    "category": "InfoLit",
    "tags": [
      "InfoLit"
    ],
    "updatedAt": "2026-07-03T00:00:00.000Z"
  },
  {
    "id": "in-glossary-054",
    "term": "IL概念53",
    "definition": "IL概念53说明",
    "category": "InfoLit",
    "tags": [
      "InfoLit"
    ],
    "updatedAt": "2026-07-03T00:00:00.000Z"
  },
  {
    "id": "in-glossary-055",
    "term": "IL概念54",
    "definition": "IL概念54说明",
    "category": "InfoLit",
    "tags": [
      "InfoLit"
    ],
    "updatedAt": "2026-07-03T00:00:00.000Z"
  },
  {
    "id": "in-glossary-056",
    "term": "IL概念55",
    "definition": "IL概念55说明",
    "category": "InfoLit",
    "tags": [
      "InfoLit"
    ],
    "updatedAt": "2026-07-03T00:00:00.000Z"
  },
  {
    "id": "in-glossary-057",
    "term": "IL概念56",
    "definition": "IL概念56说明",
    "category": "InfoLit",
    "tags": [
      "InfoLit"
    ],
    "updatedAt": "2026-07-03T00:00:00.000Z"
  },
  {
    "id": "in-glossary-058",
    "term": "IL概念57",
    "definition": "IL概念57说明",
    "category": "InfoLit",
    "tags": [
      "InfoLit"
    ],
    "updatedAt": "2026-07-03T00:00:00.000Z"
  },
  {
    "id": "in-glossary-059",
    "term": "IL概念58",
    "definition": "IL概念58说明",
    "category": "InfoLit",
    "tags": [
      "InfoLit"
    ],
    "updatedAt": "2026-07-03T00:00:00.000Z"
  },
  {
    "id": "in-glossary-060",
    "term": "IL概念59",
    "definition": "IL概念59说明",
    "category": "InfoLit",
    "tags": [
      "InfoLit"
    ],
    "updatedAt": "2026-07-03T00:00:00.000Z"
  },
  {
    "id": "in-glossary-061",
    "term": "IL概念60",
    "definition": "IL概念60说明",
    "category": "InfoLit",
    "tags": [
      "InfoLit"
    ],
    "updatedAt": "2026-07-03T00:00:00.000Z"
  },
  {
    "id": "in-glossary-062",
    "term": "IL概念61",
    "definition": "IL概念61说明",
    "category": "InfoLit",
    "tags": [
      "InfoLit"
    ],
    "updatedAt": "2026-07-03T00:00:00.000Z"
  },
  {
    "id": "in-glossary-063",
    "term": "IL概念62",
    "definition": "IL概念62说明",
    "category": "InfoLit",
    "tags": [
      "InfoLit"
    ],
    "updatedAt": "2026-07-03T00:00:00.000Z"
  },
  {
    "id": "in-glossary-064",
    "term": "IL概念63",
    "definition": "IL概念63说明",
    "category": "InfoLit",
    "tags": [
      "InfoLit"
    ],
    "updatedAt": "2026-07-03T00:00:00.000Z"
  },
  {
    "id": "in-glossary-065",
    "term": "IL概念64",
    "definition": "IL概念64说明",
    "category": "InfoLit",
    "tags": [
      "InfoLit"
    ],
    "updatedAt": "2026-07-03T00:00:00.000Z"
  },
  {
    "id": "in-glossary-066",
    "term": "IL概念65",
    "definition": "IL概念65说明",
    "category": "InfoLit",
    "tags": [
      "InfoLit"
    ],
    "updatedAt": "2026-07-03T00:00:00.000Z"
  },
  {
    "id": "in-glossary-067",
    "term": "IL概念66",
    "definition": "IL概念66说明",
    "category": "InfoLit",
    "tags": [
      "InfoLit"
    ],
    "updatedAt": "2026-07-03T00:00:00.000Z"
  },
  {
    "id": "in-glossary-068",
    "term": "IL概念67",
    "definition": "IL概念67说明",
    "category": "InfoLit",
    "tags": [
      "InfoLit"
    ],
    "updatedAt": "2026-07-03T00:00:00.000Z"
  },
  {
    "id": "in-glossary-069",
    "term": "IL概念68",
    "definition": "IL概念68说明",
    "category": "InfoLit",
    "tags": [
      "InfoLit"
    ],
    "updatedAt": "2026-07-03T00:00:00.000Z"
  },
  {
    "id": "in-glossary-070",
    "term": "IL概念69",
    "definition": "IL概念69说明",
    "category": "InfoLit",
    "tags": [
      "InfoLit"
    ],
    "updatedAt": "2026-07-03T00:00:00.000Z"
  },
  {
    "id": "in-glossary-071",
    "term": "IL概念70",
    "definition": "IL概念70说明",
    "category": "InfoLit",
    "tags": [
      "InfoLit"
    ],
    "updatedAt": "2026-07-03T00:00:00.000Z"
  },
  {
    "id": "in-glossary-072",
    "term": "IL概念71",
    "definition": "IL概念71说明",
    "category": "InfoLit",
    "tags": [
      "InfoLit"
    ],
    "updatedAt": "2026-07-03T00:00:00.000Z"
  },
  {
    "id": "in-glossary-073",
    "term": "IL概念72",
    "definition": "IL概念72说明",
    "category": "InfoLit",
    "tags": [
      "InfoLit"
    ],
    "updatedAt": "2026-07-03T00:00:00.000Z"
  },
  {
    "id": "in-glossary-074",
    "term": "IL概念73",
    "definition": "IL概念73说明",
    "category": "InfoLit",
    "tags": [
      "InfoLit"
    ],
    "updatedAt": "2026-07-03T00:00:00.000Z"
  },
  {
    "id": "in-glossary-075",
    "term": "IL概念74",
    "definition": "IL概念74说明",
    "category": "InfoLit",
    "tags": [
      "InfoLit"
    ],
    "updatedAt": "2026-07-03T00:00:00.000Z"
  },
  {
    "id": "in-glossary-076",
    "term": "IL概念75",
    "definition": "IL概念75说明",
    "category": "InfoLit",
    "tags": [
      "InfoLit"
    ],
    "updatedAt": "2026-07-03T00:00:00.000Z"
  },
  {
    "id": "in-glossary-077",
    "term": "IL概念76",
    "definition": "IL概念76说明",
    "category": "InfoLit",
    "tags": [
      "InfoLit"
    ],
    "updatedAt": "2026-07-03T00:00:00.000Z"
  },
  {
    "id": "in-glossary-078",
    "term": "IL概念77",
    "definition": "IL概念77说明",
    "category": "InfoLit",
    "tags": [
      "InfoLit"
    ],
    "updatedAt": "2026-07-03T00:00:00.000Z"
  },
  {
    "id": "in-glossary-079",
    "term": "IL概念78",
    "definition": "IL概念78说明",
    "category": "InfoLit",
    "tags": [
      "InfoLit"
    ],
    "updatedAt": "2026-07-03T00:00:00.000Z"
  },
  {
    "id": "in-glossary-080",
    "term": "IL概念79",
    "definition": "IL概念79说明",
    "category": "InfoLit",
    "tags": [
      "InfoLit"
    ],
    "updatedAt": "2026-07-03T00:00:00.000Z"
  },
  {
    "id": "in-glossary-081",
    "term": "IL概念80",
    "definition": "IL概念80说明",
    "category": "InfoLit",
    "tags": [
      "InfoLit"
    ],
    "updatedAt": "2026-07-03T00:00:00.000Z"
  },
  {
    "id": "in-glossary-082",
    "term": "IL概念81",
    "definition": "IL概念81说明",
    "category": "InfoLit",
    "tags": [
      "InfoLit"
    ],
    "updatedAt": "2026-07-03T00:00:00.000Z"
  },
  {
    "id": "in-glossary-083",
    "term": "IL概念82",
    "definition": "IL概念82说明",
    "category": "InfoLit",
    "tags": [
      "InfoLit"
    ],
    "updatedAt": "2026-07-03T00:00:00.000Z"
  },
  {
    "id": "in-glossary-084",
    "term": "IL概念83",
    "definition": "IL概念83说明",
    "category": "InfoLit",
    "tags": [
      "InfoLit"
    ],
    "updatedAt": "2026-07-03T00:00:00.000Z"
  },
  {
    "id": "in-glossary-085",
    "term": "IL概念84",
    "definition": "IL概念84说明",
    "category": "InfoLit",
    "tags": [
      "InfoLit"
    ],
    "updatedAt": "2026-07-03T00:00:00.000Z"
  },
  {
    "id": "in-glossary-086",
    "term": "IL概念85",
    "definition": "IL概念85说明",
    "category": "InfoLit",
    "tags": [
      "InfoLit"
    ],
    "updatedAt": "2026-07-03T00:00:00.000Z"
  },
  {
    "id": "in-glossary-087",
    "term": "IL概念86",
    "definition": "IL概念86说明",
    "category": "InfoLit",
    "tags": [
      "InfoLit"
    ],
    "updatedAt": "2026-07-03T00:00:00.000Z"
  },
  {
    "id": "in-glossary-088",
    "term": "IL概念87",
    "definition": "IL概念87说明",
    "category": "InfoLit",
    "tags": [
      "InfoLit"
    ],
    "updatedAt": "2026-07-03T00:00:00.000Z"
  },
  {
    "id": "in-glossary-089",
    "term": "IL概念88",
    "definition": "IL概念88说明",
    "category": "InfoLit",
    "tags": [
      "InfoLit"
    ],
    "updatedAt": "2026-07-03T00:00:00.000Z"
  },
  {
    "id": "in-glossary-090",
    "term": "IL概念89",
    "definition": "IL概念89说明",
    "category": "InfoLit",
    "tags": [
      "InfoLit"
    ],
    "updatedAt": "2026-07-03T00:00:00.000Z"
  },
  {
    "id": "in-glossary-091",
    "term": "IL概念90",
    "definition": "IL概念90说明",
    "category": "InfoLit",
    "tags": [
      "InfoLit"
    ],
    "updatedAt": "2026-07-03T00:00:00.000Z"
  },
  {
    "id": "in-glossary-092",
    "term": "IL概念91",
    "definition": "IL概念91说明",
    "category": "InfoLit",
    "tags": [
      "InfoLit"
    ],
    "updatedAt": "2026-07-03T00:00:00.000Z"
  },
  {
    "id": "in-glossary-093",
    "term": "IL概念92",
    "definition": "IL概念92说明",
    "category": "InfoLit",
    "tags": [
      "InfoLit"
    ],
    "updatedAt": "2026-07-03T00:00:00.000Z"
  },
  {
    "id": "in-glossary-094",
    "term": "IL概念93",
    "definition": "IL概念93说明",
    "category": "InfoLit",
    "tags": [
      "InfoLit"
    ],
    "updatedAt": "2026-07-03T00:00:00.000Z"
  },
  {
    "id": "in-glossary-095",
    "term": "IL概念94",
    "definition": "IL概念94说明",
    "category": "InfoLit",
    "tags": [
      "InfoLit"
    ],
    "updatedAt": "2026-07-03T00:00:00.000Z"
  },
  {
    "id": "in-glossary-096",
    "term": "IL概念95",
    "definition": "IL概念95说明",
    "category": "InfoLit",
    "tags": [
      "InfoLit"
    ],
    "updatedAt": "2026-07-03T00:00:00.000Z"
  },
  {
    "id": "in-glossary-097",
    "term": "IL概念96",
    "definition": "IL概念96说明",
    "category": "InfoLit",
    "tags": [
      "InfoLit"
    ],
    "updatedAt": "2026-07-03T00:00:00.000Z"
  },
  {
    "id": "in-glossary-098",
    "term": "IL概念97",
    "definition": "IL概念97说明",
    "category": "InfoLit",
    "tags": [
      "InfoLit"
    ],
    "updatedAt": "2026-07-03T00:00:00.000Z"
  },
  {
    "id": "in-glossary-099",
    "term": "IL概念98",
    "definition": "IL概念98说明",
    "category": "InfoLit",
    "tags": [
      "InfoLit"
    ],
    "updatedAt": "2026-07-03T00:00:00.000Z"
  },
  {
    "id": "in-glossary-100",
    "term": "IL概念99",
    "definition": "IL概念99说明",
    "category": "InfoLit",
    "tags": [
      "InfoLit"
    ],
    "updatedAt": "2026-07-03T00:00:00.000Z"
  },
  {
    "id": "in-glossary-101",
    "term": "IL概念100",
    "definition": "IL概念100说明",
    "category": "InfoLit",
    "tags": [
      "InfoLit"
    ],
    "updatedAt": "2026-07-03T00:00:00.000Z"
  },
  {
    "id": "in-glossary-102",
    "term": "IL概念101",
    "definition": "IL概念101说明",
    "category": "InfoLit",
    "tags": [
      "InfoLit"
    ],
    "updatedAt": "2026-07-03T00:00:00.000Z"
  },
  {
    "id": "in-glossary-103",
    "term": "IL概念102",
    "definition": "IL概念102说明",
    "category": "InfoLit",
    "tags": [
      "InfoLit"
    ],
    "updatedAt": "2026-07-03T00:00:00.000Z"
  },
  {
    "id": "in-glossary-104",
    "term": "IL概念103",
    "definition": "IL概念103说明",
    "category": "InfoLit",
    "tags": [
      "InfoLit"
    ],
    "updatedAt": "2026-07-03T00:00:00.000Z"
  },
  {
    "id": "in-glossary-105",
    "term": "IL概念104",
    "definition": "IL概念104说明",
    "category": "InfoLit",
    "tags": [
      "InfoLit"
    ],
    "updatedAt": "2026-07-03T00:00:00.000Z"
  },
  {
    "id": "in-glossary-106",
    "term": "IL概念105",
    "definition": "IL概念105说明",
    "category": "InfoLit",
    "tags": [
      "InfoLit"
    ],
    "updatedAt": "2026-07-03T00:00:00.000Z"
  },
  {
    "id": "in-glossary-107",
    "term": "IL概念106",
    "definition": "IL概念106说明",
    "category": "InfoLit",
    "tags": [
      "InfoLit"
    ],
    "updatedAt": "2026-07-03T00:00:00.000Z"
  },
  {
    "id": "in-glossary-108",
    "term": "IL概念107",
    "definition": "IL概念107说明",
    "category": "InfoLit",
    "tags": [
      "InfoLit"
    ],
    "updatedAt": "2026-07-03T00:00:00.000Z"
  },
  {
    "id": "in-glossary-109",
    "term": "IL概念108",
    "definition": "IL概念108说明",
    "category": "InfoLit",
    "tags": [
      "InfoLit"
    ],
    "updatedAt": "2026-07-03T00:00:00.000Z"
  },
  {
    "id": "in-glossary-110",
    "term": "IL概念109",
    "definition": "IL概念109说明",
    "category": "InfoLit",
    "tags": [
      "InfoLit"
    ],
    "updatedAt": "2026-07-03T00:00:00.000Z"
  },
  {
    "id": "in-glossary-111",
    "term": "IL概念110",
    "definition": "IL概念110说明",
    "category": "InfoLit",
    "tags": [
      "InfoLit"
    ],
    "updatedAt": "2026-07-03T00:00:00.000Z"
  },
  {
    "id": "in-glossary-112",
    "term": "IL概念111",
    "definition": "IL概念111说明",
    "category": "InfoLit",
    "tags": [
      "InfoLit"
    ],
    "updatedAt": "2026-07-03T00:00:00.000Z"
  },
  {
    "id": "in-glossary-113",
    "term": "IL概念112",
    "definition": "IL概念112说明",
    "category": "InfoLit",
    "tags": [
      "InfoLit"
    ],
    "updatedAt": "2026-07-03T00:00:00.000Z"
  },
  {
    "id": "in-glossary-114",
    "term": "IL概念113",
    "definition": "IL概念113说明",
    "category": "InfoLit",
    "tags": [
      "InfoLit"
    ],
    "updatedAt": "2026-07-03T00:00:00.000Z"
  },
  {
    "id": "in-glossary-115",
    "term": "IL概念114",
    "definition": "IL概念114说明",
    "category": "InfoLit",
    "tags": [
      "InfoLit"
    ],
    "updatedAt": "2026-07-03T00:00:00.000Z"
  },
  {
    "id": "in-glossary-116",
    "term": "IL概念115",
    "definition": "IL概念115说明",
    "category": "InfoLit",
    "tags": [
      "InfoLit"
    ],
    "updatedAt": "2026-07-03T00:00:00.000Z"
  },
  {
    "id": "in-glossary-117",
    "term": "IL概念116",
    "definition": "IL概念116说明",
    "category": "InfoLit",
    "tags": [
      "InfoLit"
    ],
    "updatedAt": "2026-07-03T00:00:00.000Z"
  },
  {
    "id": "in-glossary-118",
    "term": "IL概念117",
    "definition": "IL概念117说明",
    "category": "InfoLit",
    "tags": [
      "InfoLit"
    ],
    "updatedAt": "2026-07-03T00:00:00.000Z"
  },
  {
    "id": "in-glossary-119",
    "term": "IL概念118",
    "definition": "IL概念118说明",
    "category": "InfoLit",
    "tags": [
      "InfoLit"
    ],
    "updatedAt": "2026-07-03T00:00:00.000Z"
  },
  {
    "id": "in-glossary-120",
    "term": "IL概念119",
    "definition": "IL概念119说明",
    "category": "InfoLit",
    "tags": [
      "InfoLit"
    ],
    "updatedAt": "2026-07-03T00:00:00.000Z"
  },
  {
    "id": "in-glossary-121",
    "term": "IL概念120",
    "definition": "IL概念120说明",
    "category": "InfoLit",
    "tags": [
      "InfoLit"
    ],
    "updatedAt": "2026-07-03T00:00:00.000Z"
  },
  {
    "id": "in-glossary-122",
    "term": "IL概念121",
    "definition": "IL概念121说明",
    "category": "InfoLit",
    "tags": [
      "InfoLit"
    ],
    "updatedAt": "2026-07-03T00:00:00.000Z"
  },
  {
    "id": "in-glossary-123",
    "term": "IL概念122",
    "definition": "IL概念122说明",
    "category": "InfoLit",
    "tags": [
      "InfoLit"
    ],
    "updatedAt": "2026-07-03T00:00:00.000Z"
  },
  {
    "id": "in-glossary-124",
    "term": "IL概念123",
    "definition": "IL概念123说明",
    "category": "InfoLit",
    "tags": [
      "InfoLit"
    ],
    "updatedAt": "2026-07-03T00:00:00.000Z"
  },
  {
    "id": "in-glossary-125",
    "term": "IL概念124",
    "definition": "IL概念124说明",
    "category": "InfoLit",
    "tags": [
      "InfoLit"
    ],
    "updatedAt": "2026-07-03T00:00:00.000Z"
  },
  {
    "id": "in-glossary-126",
    "term": "IL概念125",
    "definition": "IL概念125说明",
    "category": "InfoLit",
    "tags": [
      "InfoLit"
    ],
    "updatedAt": "2026-07-03T00:00:00.000Z"
  },
  {
    "id": "in-glossary-127",
    "term": "IL概念126",
    "definition": "IL概念126说明",
    "category": "InfoLit",
    "tags": [
      "InfoLit"
    ],
    "updatedAt": "2026-07-03T00:00:00.000Z"
  },
  {
    "id": "in-glossary-128",
    "term": "IL概念127",
    "definition": "IL概念127说明",
    "category": "InfoLit",
    "tags": [
      "InfoLit"
    ],
    "updatedAt": "2026-07-03T00:00:00.000Z"
  },
  {
    "id": "in-glossary-129",
    "term": "IL概念128",
    "definition": "IL概念128说明",
    "category": "InfoLit",
    "tags": [
      "InfoLit"
    ],
    "updatedAt": "2026-07-03T00:00:00.000Z"
  },
  {
    "id": "in-glossary-130",
    "term": "IL概念129",
    "definition": "IL概念129说明",
    "category": "InfoLit",
    "tags": [
      "InfoLit"
    ],
    "updatedAt": "2026-07-03T00:00:00.000Z"
  },
  {
    "id": "in-glossary-131",
    "term": "IL概念130",
    "definition": "IL概念130说明",
    "category": "InfoLit",
    "tags": [
      "InfoLit"
    ],
    "updatedAt": "2026-07-03T00:00:00.000Z"
  },
  {
    "id": "in-glossary-132",
    "term": "IL概念131",
    "definition": "IL概念131说明",
    "category": "InfoLit",
    "tags": [
      "InfoLit"
    ],
    "updatedAt": "2026-07-03T00:00:00.000Z"
  },
  {
    "id": "in-glossary-133",
    "term": "IL概念132",
    "definition": "IL概念132说明",
    "category": "InfoLit",
    "tags": [
      "InfoLit"
    ],
    "updatedAt": "2026-07-03T00:00:00.000Z"
  },
  {
    "id": "in-glossary-134",
    "term": "IL概念133",
    "definition": "IL概念133说明",
    "category": "InfoLit",
    "tags": [
      "InfoLit"
    ],
    "updatedAt": "2026-07-03T00:00:00.000Z"
  },
  {
    "id": "in-glossary-135",
    "term": "IL概念134",
    "definition": "IL概念134说明",
    "category": "InfoLit",
    "tags": [
      "InfoLit"
    ],
    "updatedAt": "2026-07-03T00:00:00.000Z"
  },
  {
    "id": "in-glossary-136",
    "term": "IL概念135",
    "definition": "IL概念135说明",
    "category": "InfoLit",
    "tags": [
      "InfoLit"
    ],
    "updatedAt": "2026-07-03T00:00:00.000Z"
  },
  {
    "id": "in-glossary-137",
    "term": "IL概念136",
    "definition": "IL概念136说明",
    "category": "InfoLit",
    "tags": [
      "InfoLit"
    ],
    "updatedAt": "2026-07-03T00:00:00.000Z"
  },
  {
    "id": "in-glossary-138",
    "term": "IL概念137",
    "definition": "IL概念137说明",
    "category": "InfoLit",
    "tags": [
      "InfoLit"
    ],
    "updatedAt": "2026-07-03T00:00:00.000Z"
  },
  {
    "id": "in-glossary-139",
    "term": "IL概念138",
    "definition": "IL概念138说明",
    "category": "InfoLit",
    "tags": [
      "InfoLit"
    ],
    "updatedAt": "2026-07-03T00:00:00.000Z"
  },
  {
    "id": "in-glossary-140",
    "term": "IL概念139",
    "definition": "IL概念139说明",
    "category": "InfoLit",
    "tags": [
      "InfoLit"
    ],
    "updatedAt": "2026-07-03T00:00:00.000Z"
  },
  {
    "id": "in-glossary-141",
    "term": "IL概念140",
    "definition": "IL概念140说明",
    "category": "InfoLit",
    "tags": [
      "InfoLit"
    ],
    "updatedAt": "2026-07-03T00:00:00.000Z"
  },
  {
    "id": "in-glossary-142",
    "term": "IL概念141",
    "definition": "IL概念141说明",
    "category": "InfoLit",
    "tags": [
      "InfoLit"
    ],
    "updatedAt": "2026-07-03T00:00:00.000Z"
  },
  {
    "id": "in-glossary-143",
    "term": "IL概念142",
    "definition": "IL概念142说明",
    "category": "InfoLit",
    "tags": [
      "InfoLit"
    ],
    "updatedAt": "2026-07-03T00:00:00.000Z"
  },
  {
    "id": "in-glossary-144",
    "term": "IL概念143",
    "definition": "IL概念143说明",
    "category": "InfoLit",
    "tags": [
      "InfoLit"
    ],
    "updatedAt": "2026-07-03T00:00:00.000Z"
  },
  {
    "id": "in-glossary-145",
    "term": "IL概念144",
    "definition": "IL概念144说明",
    "category": "InfoLit",
    "tags": [
      "InfoLit"
    ],
    "updatedAt": "2026-07-03T00:00:00.000Z"
  },
  {
    "id": "in-glossary-146",
    "term": "IL概念145",
    "definition": "IL概念145说明",
    "category": "InfoLit",
    "tags": [
      "InfoLit"
    ],
    "updatedAt": "2026-07-03T00:00:00.000Z"
  },
  {
    "id": "in-glossary-147",
    "term": "IL概念146",
    "definition": "IL概念146说明",
    "category": "InfoLit",
    "tags": [
      "InfoLit"
    ],
    "updatedAt": "2026-07-03T00:00:00.000Z"
  },
  {
    "id": "in-glossary-148",
    "term": "IL概念147",
    "definition": "IL概念147说明",
    "category": "InfoLit",
    "tags": [
      "InfoLit"
    ],
    "updatedAt": "2026-07-03T00:00:00.000Z"
  },
  {
    "id": "in-glossary-149",
    "term": "IL概念148",
    "definition": "IL概念148说明",
    "category": "InfoLit",
    "tags": [
      "InfoLit"
    ],
    "updatedAt": "2026-07-03T00:00:00.000Z"
  },
  {
    "id": "in-glossary-150",
    "term": "IL概念149",
    "definition": "IL概念149说明",
    "category": "InfoLit",
    "tags": [
      "InfoLit"
    ],
    "updatedAt": "2026-07-03T00:00:00.000Z"
  },
  {
    "id": "in-glossary-151",
    "term": "IL概念150",
    "definition": "IL概念150说明",
    "category": "InfoLit",
    "tags": [
      "InfoLit"
    ],
    "updatedAt": "2026-07-03T00:00:00.000Z"
  },
  {
    "id": "in-glossary-152",
    "term": "IL概念151",
    "definition": "IL概念151说明",
    "category": "InfoLit",
    "tags": [
      "InfoLit"
    ],
    "updatedAt": "2026-07-03T00:00:00.000Z"
  },
  {
    "id": "in-glossary-153",
    "term": "IL概念152",
    "definition": "IL概念152说明",
    "category": "InfoLit",
    "tags": [
      "InfoLit"
    ],
    "updatedAt": "2026-07-03T00:00:00.000Z"
  },
  {
    "id": "in-glossary-154",
    "term": "IL概念153",
    "definition": "IL概念153说明",
    "category": "InfoLit",
    "tags": [
      "InfoLit"
    ],
    "updatedAt": "2026-07-03T00:00:00.000Z"
  },
  {
    "id": "in-glossary-155",
    "term": "IL概念154",
    "definition": "IL概念154说明",
    "category": "InfoLit",
    "tags": [
      "InfoLit"
    ],
    "updatedAt": "2026-07-03T00:00:00.000Z"
  },
  {
    "id": "in-glossary-156",
    "term": "IL概念155",
    "definition": "IL概念155说明",
    "category": "InfoLit",
    "tags": [
      "InfoLit"
    ],
    "updatedAt": "2026-07-03T00:00:00.000Z"
  },
  {
    "id": "in-glossary-157",
    "term": "IL概念156",
    "definition": "IL概念156说明",
    "category": "InfoLit",
    "tags": [
      "InfoLit"
    ],
    "updatedAt": "2026-07-03T00:00:00.000Z"
  },
  {
    "id": "in-glossary-158",
    "term": "IL概念157",
    "definition": "IL概念157说明",
    "category": "InfoLit",
    "tags": [
      "InfoLit"
    ],
    "updatedAt": "2026-07-03T00:00:00.000Z"
  },
  {
    "id": "in-glossary-159",
    "term": "IL概念158",
    "definition": "IL概念158说明",
    "category": "InfoLit",
    "tags": [
      "InfoLit"
    ],
    "updatedAt": "2026-07-03T00:00:00.000Z"
  },
  {
    "id": "in-glossary-160",
    "term": "IL概念159",
    "definition": "IL概念159说明",
    "category": "InfoLit",
    "tags": [
      "InfoLit"
    ],
    "updatedAt": "2026-07-03T00:00:00.000Z"
  },
  {
    "id": "in-glossary-161",
    "term": "IL概念160",
    "definition": "IL概念160说明",
    "category": "InfoLit",
    "tags": [
      "InfoLit"
    ],
    "updatedAt": "2026-07-03T00:00:00.000Z"
  },
  {
    "id": "in-glossary-162",
    "term": "IL概念161",
    "definition": "IL概念161说明",
    "category": "InfoLit",
    "tags": [
      "InfoLit"
    ],
    "updatedAt": "2026-07-03T00:00:00.000Z"
  },
  {
    "id": "in-glossary-163",
    "term": "IL概念162",
    "definition": "IL概念162说明",
    "category": "InfoLit",
    "tags": [
      "InfoLit"
    ],
    "updatedAt": "2026-07-03T00:00:00.000Z"
  },
  {
    "id": "in-glossary-164",
    "term": "IL概念163",
    "definition": "IL概念163说明",
    "category": "InfoLit",
    "tags": [
      "InfoLit"
    ],
    "updatedAt": "2026-07-03T00:00:00.000Z"
  },
  {
    "id": "in-glossary-165",
    "term": "IL概念164",
    "definition": "IL概念164说明",
    "category": "InfoLit",
    "tags": [
      "InfoLit"
    ],
    "updatedAt": "2026-07-03T00:00:00.000Z"
  },
  {
    "id": "in-glossary-166",
    "term": "IL概念165",
    "definition": "IL概念165说明",
    "category": "InfoLit",
    "tags": [
      "InfoLit"
    ],
    "updatedAt": "2026-07-03T00:00:00.000Z"
  },
  {
    "id": "in-glossary-167",
    "term": "IL概念166",
    "definition": "IL概念166说明",
    "category": "InfoLit",
    "tags": [
      "InfoLit"
    ],
    "updatedAt": "2026-07-03T00:00:00.000Z"
  },
  {
    "id": "in-glossary-168",
    "term": "IL概念167",
    "definition": "IL概念167说明",
    "category": "InfoLit",
    "tags": [
      "InfoLit"
    ],
    "updatedAt": "2026-07-03T00:00:00.000Z"
  },
  {
    "id": "in-glossary-169",
    "term": "IL概念168",
    "definition": "IL概念168说明",
    "category": "InfoLit",
    "tags": [
      "InfoLit"
    ],
    "updatedAt": "2026-07-03T00:00:00.000Z"
  },
  {
    "id": "in-glossary-170",
    "term": "IL概念169",
    "definition": "IL概念169说明",
    "category": "InfoLit",
    "tags": [
      "InfoLit"
    ],
    "updatedAt": "2026-07-03T00:00:00.000Z"
  },
  {
    "id": "in-glossary-171",
    "term": "IL概念170",
    "definition": "IL概念170说明",
    "category": "InfoLit",
    "tags": [
      "InfoLit"
    ],
    "updatedAt": "2026-07-03T00:00:00.000Z"
  },
  {
    "id": "in-glossary-172",
    "term": "IL概念171",
    "definition": "IL概念171说明",
    "category": "InfoLit",
    "tags": [
      "InfoLit"
    ],
    "updatedAt": "2026-07-03T00:00:00.000Z"
  },
  {
    "id": "in-glossary-173",
    "term": "IL概念172",
    "definition": "IL概念172说明",
    "category": "InfoLit",
    "tags": [
      "InfoLit"
    ],
    "updatedAt": "2026-07-03T00:00:00.000Z"
  },
  {
    "id": "in-glossary-174",
    "term": "IL概念173",
    "definition": "IL概念173说明",
    "category": "InfoLit",
    "tags": [
      "InfoLit"
    ],
    "updatedAt": "2026-07-03T00:00:00.000Z"
  },
  {
    "id": "in-glossary-175",
    "term": "IL概念174",
    "definition": "IL概念174说明",
    "category": "InfoLit",
    "tags": [
      "InfoLit"
    ],
    "updatedAt": "2026-07-03T00:00:00.000Z"
  },
  {
    "id": "in-glossary-176",
    "term": "IL概念175",
    "definition": "IL概念175说明",
    "category": "InfoLit",
    "tags": [
      "InfoLit"
    ],
    "updatedAt": "2026-07-03T00:00:00.000Z"
  },
  {
    "id": "in-glossary-177",
    "term": "IL概念176",
    "definition": "IL概念176说明",
    "category": "InfoLit",
    "tags": [
      "InfoLit"
    ],
    "updatedAt": "2026-07-03T00:00:00.000Z"
  },
  {
    "id": "in-glossary-178",
    "term": "IL概念177",
    "definition": "IL概念177说明",
    "category": "InfoLit",
    "tags": [
      "InfoLit"
    ],
    "updatedAt": "2026-07-03T00:00:00.000Z"
  },
  {
    "id": "in-glossary-179",
    "term": "IL概念178",
    "definition": "IL概念178说明",
    "category": "InfoLit",
    "tags": [
      "InfoLit"
    ],
    "updatedAt": "2026-07-03T00:00:00.000Z"
  },
  {
    "id": "in-glossary-180",
    "term": "IL概念179",
    "definition": "IL概念179说明",
    "category": "InfoLit",
    "tags": [
      "InfoLit"
    ],
    "updatedAt": "2026-07-03T00:00:00.000Z"
  },
  {
    "id": "in-glossary-181",
    "term": "IL概念180",
    "definition": "IL概念180说明",
    "category": "InfoLit",
    "tags": [
      "InfoLit"
    ],
    "updatedAt": "2026-07-03T00:00:00.000Z"
  },
  {
    "id": "in-glossary-182",
    "term": "IL概念181",
    "definition": "IL概念181说明",
    "category": "InfoLit",
    "tags": [
      "InfoLit"
    ],
    "updatedAt": "2026-07-03T00:00:00.000Z"
  },
  {
    "id": "in-glossary-183",
    "term": "IL概念182",
    "definition": "IL概念182说明",
    "category": "InfoLit",
    "tags": [
      "InfoLit"
    ],
    "updatedAt": "2026-07-03T00:00:00.000Z"
  },
  {
    "id": "in-glossary-184",
    "term": "IL概念183",
    "definition": "IL概念183说明",
    "category": "InfoLit",
    "tags": [
      "InfoLit"
    ],
    "updatedAt": "2026-07-03T00:00:00.000Z"
  },
  {
    "id": "in-glossary-185",
    "term": "IL概念184",
    "definition": "IL概念184说明",
    "category": "InfoLit",
    "tags": [
      "InfoLit"
    ],
    "updatedAt": "2026-07-03T00:00:00.000Z"
  },
  {
    "id": "in-glossary-186",
    "term": "IL概念185",
    "definition": "IL概念185说明",
    "category": "InfoLit",
    "tags": [
      "InfoLit"
    ],
    "updatedAt": "2026-07-03T00:00:00.000Z"
  },
  {
    "id": "in-glossary-187",
    "term": "IL概念186",
    "definition": "IL概念186说明",
    "category": "InfoLit",
    "tags": [
      "InfoLit"
    ],
    "updatedAt": "2026-07-03T00:00:00.000Z"
  },
  {
    "id": "in-glossary-188",
    "term": "IL概念187",
    "definition": "IL概念187说明",
    "category": "InfoLit",
    "tags": [
      "InfoLit"
    ],
    "updatedAt": "2026-07-03T00:00:00.000Z"
  },
  {
    "id": "in-glossary-189",
    "term": "IL概念188",
    "definition": "IL概念188说明",
    "category": "InfoLit",
    "tags": [
      "InfoLit"
    ],
    "updatedAt": "2026-07-03T00:00:00.000Z"
  },
  {
    "id": "in-glossary-190",
    "term": "IL概念189",
    "definition": "IL概念189说明",
    "category": "InfoLit",
    "tags": [
      "InfoLit"
    ],
    "updatedAt": "2026-07-03T00:00:00.000Z"
  },
  {
    "id": "in-glossary-191",
    "term": "IL概念190",
    "definition": "IL概念190说明",
    "category": "InfoLit",
    "tags": [
      "InfoLit"
    ],
    "updatedAt": "2026-07-03T00:00:00.000Z"
  },
  {
    "id": "in-glossary-192",
    "term": "IL概念191",
    "definition": "IL概念191说明",
    "category": "InfoLit",
    "tags": [
      "InfoLit"
    ],
    "updatedAt": "2026-07-03T00:00:00.000Z"
  },
  {
    "id": "in-glossary-193",
    "term": "IL概念192",
    "definition": "IL概念192说明",
    "category": "InfoLit",
    "tags": [
      "InfoLit"
    ],
    "updatedAt": "2026-07-03T00:00:00.000Z"
  },
  {
    "id": "in-glossary-194",
    "term": "IL概念193",
    "definition": "IL概念193说明",
    "category": "InfoLit",
    "tags": [
      "InfoLit"
    ],
    "updatedAt": "2026-07-03T00:00:00.000Z"
  },
  {
    "id": "in-glossary-195",
    "term": "IL概念194",
    "definition": "IL概念194说明",
    "category": "InfoLit",
    "tags": [
      "InfoLit"
    ],
    "updatedAt": "2026-07-03T00:00:00.000Z"
  },
  {
    "id": "in-glossary-196",
    "term": "IL概念195",
    "definition": "IL概念195说明",
    "category": "InfoLit",
    "tags": [
      "InfoLit"
    ],
    "updatedAt": "2026-07-03T00:00:00.000Z"
  },
  {
    "id": "in-glossary-197",
    "term": "IL概念196",
    "definition": "IL概念196说明",
    "category": "InfoLit",
    "tags": [
      "InfoLit"
    ],
    "updatedAt": "2026-07-03T00:00:00.000Z"
  },
  {
    "id": "in-glossary-198",
    "term": "IL概念197",
    "definition": "IL概念197说明",
    "category": "InfoLit",
    "tags": [
      "InfoLit"
    ],
    "updatedAt": "2026-07-03T00:00:00.000Z"
  },
  {
    "id": "in-glossary-199",
    "term": "IL概念198",
    "definition": "IL概念198说明",
    "category": "InfoLit",
    "tags": [
      "InfoLit"
    ],
    "updatedAt": "2026-07-03T00:00:00.000Z"
  },
  {
    "id": "in-glossary-200",
    "term": "IL概念199",
    "definition": "IL概念199说明",
    "category": "InfoLit",
    "tags": [
      "InfoLit"
    ],
    "updatedAt": "2026-07-03T00:00:00.000Z"
  },
  {
    "id": "in-glossary-201",
    "term": "IL概念200",
    "definition": "IL概念200说明",
    "category": "InfoLit",
    "tags": [
      "InfoLit"
    ],
    "updatedAt": "2026-07-03T00:00:00.000Z"
  },
  {
    "id": "in-glossary-202",
    "term": "IL概念201",
    "definition": "IL概念201说明",
    "category": "InfoLit",
    "tags": [
      "InfoLit"
    ],
    "updatedAt": "2026-07-03T00:00:00.000Z"
  },
  {
    "id": "in-glossary-203",
    "term": "IL概念202",
    "definition": "IL概念202说明",
    "category": "InfoLit",
    "tags": [
      "InfoLit"
    ],
    "updatedAt": "2026-07-03T00:00:00.000Z"
  },
  {
    "id": "in-glossary-204",
    "term": "IL概念203",
    "definition": "IL概念203说明",
    "category": "InfoLit",
    "tags": [
      "InfoLit"
    ],
    "updatedAt": "2026-07-03T00:00:00.000Z"
  },
  {
    "id": "in-glossary-205",
    "term": "IL概念204",
    "definition": "IL概念204说明",
    "category": "InfoLit",
    "tags": [
      "InfoLit"
    ],
    "updatedAt": "2026-07-03T00:00:00.000Z"
  },
  {
    "id": "in-glossary-206",
    "term": "IL概念205",
    "definition": "IL概念205说明",
    "category": "InfoLit",
    "tags": [
      "InfoLit"
    ],
    "updatedAt": "2026-07-03T00:00:00.000Z"
  },
  {
    "id": "in-glossary-207",
    "term": "IL概念206",
    "definition": "IL概念206说明",
    "category": "InfoLit",
    "tags": [
      "InfoLit"
    ],
    "updatedAt": "2026-07-03T00:00:00.000Z"
  },
  {
    "id": "in-glossary-208",
    "term": "IL概念207",
    "definition": "IL概念207说明",
    "category": "InfoLit",
    "tags": [
      "InfoLit"
    ],
    "updatedAt": "2026-07-03T00:00:00.000Z"
  },
  {
    "id": "in-glossary-209",
    "term": "IL概念208",
    "definition": "IL概念208说明",
    "category": "InfoLit",
    "tags": [
      "InfoLit"
    ],
    "updatedAt": "2026-07-03T00:00:00.000Z"
  },
  {
    "id": "in-glossary-210",
    "term": "IL概念209",
    "definition": "IL概念209说明",
    "category": "InfoLit",
    "tags": [
      "InfoLit"
    ],
    "updatedAt": "2026-07-03T00:00:00.000Z"
  },
  {
    "id": "in-glossary-211",
    "term": "IL概念210",
    "definition": "IL概念210说明",
    "category": "InfoLit",
    "tags": [
      "InfoLit"
    ],
    "updatedAt": "2026-07-03T00:00:00.000Z"
  },
  {
    "id": "in-glossary-212",
    "term": "IL概念211",
    "definition": "IL概念211说明",
    "category": "InfoLit",
    "tags": [
      "InfoLit"
    ],
    "updatedAt": "2026-07-03T00:00:00.000Z"
  },
  {
    "id": "in-glossary-213",
    "term": "IL概念212",
    "definition": "IL概念212说明",
    "category": "InfoLit",
    "tags": [
      "InfoLit"
    ],
    "updatedAt": "2026-07-03T00:00:00.000Z"
  },
  {
    "id": "in-glossary-214",
    "term": "IL概念213",
    "definition": "IL概念213说明",
    "category": "InfoLit",
    "tags": [
      "InfoLit"
    ],
    "updatedAt": "2026-07-03T00:00:00.000Z"
  },
  {
    "id": "in-glossary-215",
    "term": "IL概念214",
    "definition": "IL概念214说明",
    "category": "InfoLit",
    "tags": [
      "InfoLit"
    ],
    "updatedAt": "2026-07-03T00:00:00.000Z"
  },
  {
    "id": "in-glossary-216",
    "term": "IL概念215",
    "definition": "IL概念215说明",
    "category": "InfoLit",
    "tags": [
      "InfoLit"
    ],
    "updatedAt": "2026-07-03T00:00:00.000Z"
  },
  {
    "id": "in-glossary-217",
    "term": "IL概念216",
    "definition": "IL概念216说明",
    "category": "InfoLit",
    "tags": [
      "InfoLit"
    ],
    "updatedAt": "2026-07-03T00:00:00.000Z"
  },
  {
    "id": "in-glossary-218",
    "term": "IL概念217",
    "definition": "IL概念217说明",
    "category": "InfoLit",
    "tags": [
      "InfoLit"
    ],
    "updatedAt": "2026-07-03T00:00:00.000Z"
  },
  {
    "id": "in-glossary-219",
    "term": "IL概念218",
    "definition": "IL概念218说明",
    "category": "InfoLit",
    "tags": [
      "InfoLit"
    ],
    "updatedAt": "2026-07-03T00:00:00.000Z"
  },
  {
    "id": "in-glossary-220",
    "term": "IL概念219",
    "definition": "IL概念219说明",
    "category": "InfoLit",
    "tags": [
      "InfoLit"
    ],
    "updatedAt": "2026-07-03T00:00:00.000Z"
  },
  {
    "id": "in-glossary-221",
    "term": "IL概念220",
    "definition": "IL概念220说明",
    "category": "InfoLit",
    "tags": [
      "InfoLit"
    ],
    "updatedAt": "2026-07-03T00:00:00.000Z"
  },
  {
    "id": "in-glossary-222",
    "term": "IL概念221",
    "definition": "IL概念221说明",
    "category": "InfoLit",
    "tags": [
      "InfoLit"
    ],
    "updatedAt": "2026-07-03T00:00:00.000Z"
  },
  {
    "id": "in-glossary-223",
    "term": "IL概念222",
    "definition": "IL概念222说明",
    "category": "InfoLit",
    "tags": [
      "InfoLit"
    ],
    "updatedAt": "2026-07-03T00:00:00.000Z"
  },
  {
    "id": "in-glossary-224",
    "term": "IL概念223",
    "definition": "IL概念223说明",
    "category": "InfoLit",
    "tags": [
      "InfoLit"
    ],
    "updatedAt": "2026-07-03T00:00:00.000Z"
  },
  {
    "id": "in-glossary-225",
    "term": "IL概念224",
    "definition": "IL概念224说明",
    "category": "InfoLit",
    "tags": [
      "InfoLit"
    ],
    "updatedAt": "2026-07-03T00:00:00.000Z"
  },
  {
    "id": "in-glossary-226",
    "term": "IL概念225",
    "definition": "IL概念225说明",
    "category": "InfoLit",
    "tags": [
      "InfoLit"
    ],
    "updatedAt": "2026-07-03T00:00:00.000Z"
  },
  {
    "id": "in-glossary-227",
    "term": "IL概念226",
    "definition": "IL概念226说明",
    "category": "InfoLit",
    "tags": [
      "InfoLit"
    ],
    "updatedAt": "2026-07-03T00:00:00.000Z"
  },
  {
    "id": "in-glossary-228",
    "term": "IL概念227",
    "definition": "IL概念227说明",
    "category": "InfoLit",
    "tags": [
      "InfoLit"
    ],
    "updatedAt": "2026-07-03T00:00:00.000Z"
  },
  {
    "id": "in-glossary-229",
    "term": "IL概念228",
    "definition": "IL概念228说明",
    "category": "InfoLit",
    "tags": [
      "InfoLit"
    ],
    "updatedAt": "2026-07-03T00:00:00.000Z"
  },
  {
    "id": "in-glossary-230",
    "term": "IL概念229",
    "definition": "IL概念229说明",
    "category": "InfoLit",
    "tags": [
      "InfoLit"
    ],
    "updatedAt": "2026-07-03T00:00:00.000Z"
  },
  {
    "id": "in-glossary-231",
    "term": "IL概念230",
    "definition": "IL概念230说明",
    "category": "InfoLit",
    "tags": [
      "InfoLit"
    ],
    "updatedAt": "2026-07-03T00:00:00.000Z"
  },
  {
    "id": "in-glossary-232",
    "term": "IL概念231",
    "definition": "IL概念231说明",
    "category": "InfoLit",
    "tags": [
      "InfoLit"
    ],
    "updatedAt": "2026-07-03T00:00:00.000Z"
  },
  {
    "id": "in-glossary-233",
    "term": "IL概念232",
    "definition": "IL概念232说明",
    "category": "InfoLit",
    "tags": [
      "InfoLit"
    ],
    "updatedAt": "2026-07-03T00:00:00.000Z"
  },
  {
    "id": "in-glossary-234",
    "term": "IL概念233",
    "definition": "IL概念233说明",
    "category": "InfoLit",
    "tags": [
      "InfoLit"
    ],
    "updatedAt": "2026-07-03T00:00:00.000Z"
  },
  {
    "id": "in-glossary-235",
    "term": "IL概念234",
    "definition": "IL概念234说明",
    "category": "InfoLit",
    "tags": [
      "InfoLit"
    ],
    "updatedAt": "2026-07-03T00:00:00.000Z"
  },
  {
    "id": "in-glossary-236",
    "term": "IL概念235",
    "definition": "IL概念235说明",
    "category": "InfoLit",
    "tags": [
      "InfoLit"
    ],
    "updatedAt": "2026-07-03T00:00:00.000Z"
  },
  {
    "id": "in-glossary-237",
    "term": "IL概念236",
    "definition": "IL概念236说明",
    "category": "InfoLit",
    "tags": [
      "InfoLit"
    ],
    "updatedAt": "2026-07-03T00:00:00.000Z"
  },
  {
    "id": "in-glossary-238",
    "term": "IL概念237",
    "definition": "IL概念237说明",
    "category": "InfoLit",
    "tags": [
      "InfoLit"
    ],
    "updatedAt": "2026-07-03T00:00:00.000Z"
  },
  {
    "id": "in-glossary-239",
    "term": "IL概念238",
    "definition": "IL概念238说明",
    "category": "InfoLit",
    "tags": [
      "InfoLit"
    ],
    "updatedAt": "2026-07-03T00:00:00.000Z"
  },
  {
    "id": "in-glossary-240",
    "term": "IL概念239",
    "definition": "IL概念239说明",
    "category": "InfoLit",
    "tags": [
      "InfoLit"
    ],
    "updatedAt": "2026-07-03T00:00:00.000Z"
  },
  {
    "id": "in-glossary-241",
    "term": "IL概念240",
    "definition": "IL概念240说明",
    "category": "InfoLit",
    "tags": [
      "InfoLit"
    ],
    "updatedAt": "2026-07-03T00:00:00.000Z"
  },
  {
    "id": "in-glossary-242",
    "term": "IL概念241",
    "definition": "IL概念241说明",
    "category": "InfoLit",
    "tags": [
      "InfoLit"
    ],
    "updatedAt": "2026-07-03T00:00:00.000Z"
  },
  {
    "id": "in-glossary-243",
    "term": "IL概念242",
    "definition": "IL概念242说明",
    "category": "InfoLit",
    "tags": [
      "InfoLit"
    ],
    "updatedAt": "2026-07-03T00:00:00.000Z"
  },
  {
    "id": "in-glossary-244",
    "term": "IL概念243",
    "definition": "IL概念243说明",
    "category": "InfoLit",
    "tags": [
      "InfoLit"
    ],
    "updatedAt": "2026-07-03T00:00:00.000Z"
  },
  {
    "id": "in-glossary-245",
    "term": "IL概念244",
    "definition": "IL概念244说明",
    "category": "InfoLit",
    "tags": [
      "InfoLit"
    ],
    "updatedAt": "2026-07-03T00:00:00.000Z"
  },
  {
    "id": "in-glossary-246",
    "term": "IL概念245",
    "definition": "IL概念245说明",
    "category": "InfoLit",
    "tags": [
      "InfoLit"
    ],
    "updatedAt": "2026-07-03T00:00:00.000Z"
  },
  {
    "id": "in-glossary-247",
    "term": "IL概念246",
    "definition": "IL概念246说明",
    "category": "InfoLit",
    "tags": [
      "InfoLit"
    ],
    "updatedAt": "2026-07-03T00:00:00.000Z"
  },
  {
    "id": "in-glossary-248",
    "term": "IL概念247",
    "definition": "IL概念247说明",
    "category": "InfoLit",
    "tags": [
      "InfoLit"
    ],
    "updatedAt": "2026-07-03T00:00:00.000Z"
  },
  {
    "id": "in-glossary-249",
    "term": "IL概念248",
    "definition": "IL概念248说明",
    "category": "InfoLit",
    "tags": [
      "InfoLit"
    ],
    "updatedAt": "2026-07-03T00:00:00.000Z"
  },
  {
    "id": "in-glossary-250",
    "term": "IL概念249",
    "definition": "IL概念249说明",
    "category": "InfoLit",
    "tags": [
      "InfoLit"
    ],
    "updatedAt": "2026-07-03T00:00:00.000Z"
  },
  {
    "id": "in-glossary-251",
    "term": "IL概念250",
    "definition": "IL概念250说明",
    "category": "InfoLit",
    "tags": [
      "InfoLit"
    ],
    "updatedAt": "2026-07-03T00:00:00.000Z"
  },
  {
    "id": "in-glossary-252",
    "term": "IL概念251",
    "definition": "IL概念251说明",
    "category": "InfoLit",
    "tags": [
      "InfoLit"
    ],
    "updatedAt": "2026-07-03T00:00:00.000Z"
  },
  {
    "id": "in-glossary-253",
    "term": "IL概念252",
    "definition": "IL概念252说明",
    "category": "InfoLit",
    "tags": [
      "InfoLit"
    ],
    "updatedAt": "2026-07-03T00:00:00.000Z"
  },
  {
    "id": "in-glossary-254",
    "term": "IL概念253",
    "definition": "IL概念253说明",
    "category": "InfoLit",
    "tags": [
      "InfoLit"
    ],
    "updatedAt": "2026-07-03T00:00:00.000Z"
  },
  {
    "id": "in-glossary-255",
    "term": "IL概念254",
    "definition": "IL概念254说明",
    "category": "InfoLit",
    "tags": [
      "InfoLit"
    ],
    "updatedAt": "2026-07-03T00:00:00.000Z"
  },
  {
    "id": "in-glossary-256",
    "term": "IL概念255",
    "definition": "IL概念255说明",
    "category": "InfoLit",
    "tags": [
      "InfoLit"
    ],
    "updatedAt": "2026-07-03T00:00:00.000Z"
  },
  {
    "id": "in-glossary-257",
    "term": "IL概念256",
    "definition": "IL概念256说明",
    "category": "InfoLit",
    "tags": [
      "InfoLit"
    ],
    "updatedAt": "2026-07-03T00:00:00.000Z"
  },
  {
    "id": "in-glossary-258",
    "term": "IL概念257",
    "definition": "IL概念257说明",
    "category": "InfoLit",
    "tags": [
      "InfoLit"
    ],
    "updatedAt": "2026-07-03T00:00:00.000Z"
  },
  {
    "id": "in-glossary-259",
    "term": "IL概念258",
    "definition": "IL概念258说明",
    "category": "InfoLit",
    "tags": [
      "InfoLit"
    ],
    "updatedAt": "2026-07-03T00:00:00.000Z"
  },
  {
    "id": "in-glossary-260",
    "term": "IL概念259",
    "definition": "IL概念259说明",
    "category": "InfoLit",
    "tags": [
      "InfoLit"
    ],
    "updatedAt": "2026-07-03T00:00:00.000Z"
  },
  {
    "id": "in-glossary-261",
    "term": "IL概念260",
    "definition": "IL概念260说明",
    "category": "InfoLit",
    "tags": [
      "InfoLit"
    ],
    "updatedAt": "2026-07-03T00:00:00.000Z"
  },
  {
    "id": "in-glossary-262",
    "term": "IL概念261",
    "definition": "IL概念261说明",
    "category": "InfoLit",
    "tags": [
      "InfoLit"
    ],
    "updatedAt": "2026-07-03T00:00:00.000Z"
  },
  {
    "id": "in-glossary-263",
    "term": "IL概念262",
    "definition": "IL概念262说明",
    "category": "InfoLit",
    "tags": [
      "InfoLit"
    ],
    "updatedAt": "2026-07-03T00:00:00.000Z"
  },
  {
    "id": "in-glossary-264",
    "term": "IL概念263",
    "definition": "IL概念263说明",
    "category": "InfoLit",
    "tags": [
      "InfoLit"
    ],
    "updatedAt": "2026-07-03T00:00:00.000Z"
  },
  {
    "id": "in-glossary-265",
    "term": "IL概念264",
    "definition": "IL概念264说明",
    "category": "InfoLit",
    "tags": [
      "InfoLit"
    ],
    "updatedAt": "2026-07-03T00:00:00.000Z"
  },
  {
    "id": "in-glossary-266",
    "term": "IL概念265",
    "definition": "IL概念265说明",
    "category": "InfoLit",
    "tags": [
      "InfoLit"
    ],
    "updatedAt": "2026-07-03T00:00:00.000Z"
  },
  {
    "id": "in-glossary-267",
    "term": "IL概念266",
    "definition": "IL概念266说明",
    "category": "InfoLit",
    "tags": [
      "InfoLit"
    ],
    "updatedAt": "2026-07-03T00:00:00.000Z"
  },
  {
    "id": "in-glossary-268",
    "term": "IL概念267",
    "definition": "IL概念267说明",
    "category": "InfoLit",
    "tags": [
      "InfoLit"
    ],
    "updatedAt": "2026-07-03T00:00:00.000Z"
  },
  {
    "id": "in-glossary-269",
    "term": "IL概念268",
    "definition": "IL概念268说明",
    "category": "InfoLit",
    "tags": [
      "InfoLit"
    ],
    "updatedAt": "2026-07-03T00:00:00.000Z"
  },
  {
    "id": "in-glossary-270",
    "term": "IL概念269",
    "definition": "IL概念269说明",
    "category": "InfoLit",
    "tags": [
      "InfoLit"
    ],
    "updatedAt": "2026-07-03T00:00:00.000Z"
  },
  {
    "id": "in-glossary-271",
    "term": "IL概念270",
    "definition": "IL概念270说明",
    "category": "InfoLit",
    "tags": [
      "InfoLit"
    ],
    "updatedAt": "2026-07-03T00:00:00.000Z"
  },
  {
    "id": "in-glossary-272",
    "term": "IL概念271",
    "definition": "IL概念271说明",
    "category": "InfoLit",
    "tags": [
      "InfoLit"
    ],
    "updatedAt": "2026-07-03T00:00:00.000Z"
  },
  {
    "id": "in-glossary-273",
    "term": "IL概念272",
    "definition": "IL概念272说明",
    "category": "InfoLit",
    "tags": [
      "InfoLit"
    ],
    "updatedAt": "2026-07-03T00:00:00.000Z"
  },
  {
    "id": "in-glossary-274",
    "term": "IL概念273",
    "definition": "IL概念273说明",
    "category": "InfoLit",
    "tags": [
      "InfoLit"
    ],
    "updatedAt": "2026-07-03T00:00:00.000Z"
  },
  {
    "id": "in-glossary-275",
    "term": "IL概念274",
    "definition": "IL概念274说明",
    "category": "InfoLit",
    "tags": [
      "InfoLit"
    ],
    "updatedAt": "2026-07-03T00:00:00.000Z"
  },
  {
    "id": "in-glossary-276",
    "term": "IL概念275",
    "definition": "IL概念275说明",
    "category": "InfoLit",
    "tags": [
      "InfoLit"
    ],
    "updatedAt": "2026-07-03T00:00:00.000Z"
  },
  {
    "id": "in-glossary-277",
    "term": "IL概念276",
    "definition": "IL概念276说明",
    "category": "InfoLit",
    "tags": [
      "InfoLit"
    ],
    "updatedAt": "2026-07-03T00:00:00.000Z"
  },
  {
    "id": "in-glossary-278",
    "term": "IL概念277",
    "definition": "IL概念277说明",
    "category": "InfoLit",
    "tags": [
      "InfoLit"
    ],
    "updatedAt": "2026-07-03T00:00:00.000Z"
  },
  {
    "id": "in-glossary-279",
    "term": "IL概念278",
    "definition": "IL概念278说明",
    "category": "InfoLit",
    "tags": [
      "InfoLit"
    ],
    "updatedAt": "2026-07-03T00:00:00.000Z"
  },
  {
    "id": "in-glossary-280",
    "term": "IL概念279",
    "definition": "IL概念279说明",
    "category": "InfoLit",
    "tags": [
      "InfoLit"
    ],
    "updatedAt": "2026-07-03T00:00:00.000Z"
  },
  {
    "id": "in-glossary-281",
    "term": "IL概念280",
    "definition": "IL概念280说明",
    "category": "InfoLit",
    "tags": [
      "InfoLit"
    ],
    "updatedAt": "2026-07-03T00:00:00.000Z"
  },
  {
    "id": "in-glossary-282",
    "term": "IL概念281",
    "definition": "IL概念281说明",
    "category": "InfoLit",
    "tags": [
      "InfoLit"
    ],
    "updatedAt": "2026-07-03T00:00:00.000Z"
  },
  {
    "id": "in-glossary-283",
    "term": "IL概念282",
    "definition": "IL概念282说明",
    "category": "InfoLit",
    "tags": [
      "InfoLit"
    ],
    "updatedAt": "2026-07-03T00:00:00.000Z"
  },
  {
    "id": "in-glossary-284",
    "term": "IL概念283",
    "definition": "IL概念283说明",
    "category": "InfoLit",
    "tags": [
      "InfoLit"
    ],
    "updatedAt": "2026-07-03T00:00:00.000Z"
  },
  {
    "id": "in-glossary-285",
    "term": "IL概念284",
    "definition": "IL概念284说明",
    "category": "InfoLit",
    "tags": [
      "InfoLit"
    ],
    "updatedAt": "2026-07-03T00:00:00.000Z"
  },
  {
    "id": "in-glossary-286",
    "term": "IL概念285",
    "definition": "IL概念285说明",
    "category": "InfoLit",
    "tags": [
      "InfoLit"
    ],
    "updatedAt": "2026-07-03T00:00:00.000Z"
  },
  {
    "id": "in-glossary-287",
    "term": "IL概念286",
    "definition": "IL概念286说明",
    "category": "InfoLit",
    "tags": [
      "InfoLit"
    ],
    "updatedAt": "2026-07-03T00:00:00.000Z"
  },
  {
    "id": "in-glossary-288",
    "term": "IL概念287",
    "definition": "IL概念287说明",
    "category": "InfoLit",
    "tags": [
      "InfoLit"
    ],
    "updatedAt": "2026-07-03T00:00:00.000Z"
  },
  {
    "id": "in-glossary-289",
    "term": "IL概念288",
    "definition": "IL概念288说明",
    "category": "InfoLit",
    "tags": [
      "InfoLit"
    ],
    "updatedAt": "2026-07-03T00:00:00.000Z"
  },
  {
    "id": "in-glossary-290",
    "term": "IL概念289",
    "definition": "IL概念289说明",
    "category": "InfoLit",
    "tags": [
      "InfoLit"
    ],
    "updatedAt": "2026-07-03T00:00:00.000Z"
  },
  {
    "id": "in-glossary-291",
    "term": "IL概念290",
    "definition": "IL概念290说明",
    "category": "InfoLit",
    "tags": [
      "InfoLit"
    ],
    "updatedAt": "2026-07-03T00:00:00.000Z"
  },
  {
    "id": "in-glossary-292",
    "term": "IL概念291",
    "definition": "IL概念291说明",
    "category": "InfoLit",
    "tags": [
      "InfoLit"
    ],
    "updatedAt": "2026-07-03T00:00:00.000Z"
  },
  {
    "id": "in-glossary-293",
    "term": "IL概念292",
    "definition": "IL概念292说明",
    "category": "InfoLit",
    "tags": [
      "InfoLit"
    ],
    "updatedAt": "2026-07-03T00:00:00.000Z"
  },
  {
    "id": "in-glossary-294",
    "term": "IL概念293",
    "definition": "IL概念293说明",
    "category": "InfoLit",
    "tags": [
      "InfoLit"
    ],
    "updatedAt": "2026-07-03T00:00:00.000Z"
  },
  {
    "id": "in-glossary-295",
    "term": "IL概念294",
    "definition": "IL概念294说明",
    "category": "InfoLit",
    "tags": [
      "InfoLit"
    ],
    "updatedAt": "2026-07-03T00:00:00.000Z"
  },
  {
    "id": "in-glossary-296",
    "term": "IL概念295",
    "definition": "IL概念295说明",
    "category": "InfoLit",
    "tags": [
      "InfoLit"
    ],
    "updatedAt": "2026-07-03T00:00:00.000Z"
  },
  {
    "id": "in-glossary-297",
    "term": "IL概念296",
    "definition": "IL概念296说明",
    "category": "InfoLit",
    "tags": [
      "InfoLit"
    ],
    "updatedAt": "2026-07-03T00:00:00.000Z"
  },
  {
    "id": "in-glossary-298",
    "term": "IL概念297",
    "definition": "IL概念297说明",
    "category": "InfoLit",
    "tags": [
      "InfoLit"
    ],
    "updatedAt": "2026-07-03T00:00:00.000Z"
  },
  {
    "id": "in-glossary-299",
    "term": "IL概念298",
    "definition": "IL概念298说明",
    "category": "InfoLit",
    "tags": [
      "InfoLit"
    ],
    "updatedAt": "2026-07-03T00:00:00.000Z"
  },
  {
    "id": "in-glossary-300",
    "term": "IL概念299",
    "definition": "IL概念299说明",
    "category": "InfoLit",
    "tags": [
      "InfoLit"
    ],
    "updatedAt": "2026-07-03T00:00:00.000Z"
  },
  {
    "id": "in-glossary-301",
    "term": "IL概念300",
    "definition": "IL概念300说明",
    "category": "InfoLit",
    "tags": [
      "InfoLit"
    ],
    "updatedAt": "2026-07-03T00:00:00.000Z"
  },
  {
    "id": "in-glossary-302",
    "term": "IL概念301",
    "definition": "IL概念301说明",
    "category": "InfoLit",
    "tags": [
      "InfoLit"
    ],
    "updatedAt": "2026-07-03T00:00:00.000Z"
  },
  {
    "id": "in-glossary-303",
    "term": "IL概念302",
    "definition": "IL概念302说明",
    "category": "InfoLit",
    "tags": [
      "InfoLit"
    ],
    "updatedAt": "2026-07-03T00:00:00.000Z"
  },
  {
    "id": "in-glossary-304",
    "term": "IL概念303",
    "definition": "IL概念303说明",
    "category": "InfoLit",
    "tags": [
      "InfoLit"
    ],
    "updatedAt": "2026-07-03T00:00:00.000Z"
  },
  {
    "id": "in-glossary-305",
    "term": "IL概念304",
    "definition": "IL概念304说明",
    "category": "InfoLit",
    "tags": [
      "InfoLit"
    ],
    "updatedAt": "2026-07-03T00:00:00.000Z"
  },
  {
    "id": "in-glossary-306",
    "term": "IL概念305",
    "definition": "IL概念305说明",
    "category": "InfoLit",
    "tags": [
      "InfoLit"
    ],
    "updatedAt": "2026-07-03T00:00:00.000Z"
  },
  {
    "id": "in-glossary-307",
    "term": "IL概念306",
    "definition": "IL概念306说明",
    "category": "InfoLit",
    "tags": [
      "InfoLit"
    ],
    "updatedAt": "2026-07-03T00:00:00.000Z"
  },
  {
    "id": "in-glossary-308",
    "term": "IL概念307",
    "definition": "IL概念307说明",
    "category": "InfoLit",
    "tags": [
      "InfoLit"
    ],
    "updatedAt": "2026-07-03T00:00:00.000Z"
  },
  {
    "id": "in-glossary-309",
    "term": "IL概念308",
    "definition": "IL概念308说明",
    "category": "InfoLit",
    "tags": [
      "InfoLit"
    ],
    "updatedAt": "2026-07-03T00:00:00.000Z"
  },
  {
    "id": "in-glossary-310",
    "term": "IL概念309",
    "definition": "IL概念309说明",
    "category": "InfoLit",
    "tags": [
      "InfoLit"
    ],
    "updatedAt": "2026-07-03T00:00:00.000Z"
  },
  {
    "id": "in-glossary-311",
    "term": "IL概念310",
    "definition": "IL概念310说明",
    "category": "InfoLit",
    "tags": [
      "InfoLit"
    ],
    "updatedAt": "2026-07-03T00:00:00.000Z"
  },
  {
    "id": "in-glossary-312",
    "term": "IL概念311",
    "definition": "IL概念311说明",
    "category": "InfoLit",
    "tags": [
      "InfoLit"
    ],
    "updatedAt": "2026-07-03T00:00:00.000Z"
  },
  {
    "id": "in-glossary-313",
    "term": "IL概念312",
    "definition": "IL概念312说明",
    "category": "InfoLit",
    "tags": [
      "InfoLit"
    ],
    "updatedAt": "2026-07-03T00:00:00.000Z"
  },
  {
    "id": "in-glossary-314",
    "term": "IL概念313",
    "definition": "IL概念313说明",
    "category": "InfoLit",
    "tags": [
      "InfoLit"
    ],
    "updatedAt": "2026-07-03T00:00:00.000Z"
  },
  {
    "id": "in-glossary-315",
    "term": "IL概念314",
    "definition": "IL概念314说明",
    "category": "InfoLit",
    "tags": [
      "InfoLit"
    ],
    "updatedAt": "2026-07-03T00:00:00.000Z"
  },
  {
    "id": "in-glossary-316",
    "term": "IL概念315",
    "definition": "IL概念315说明",
    "category": "InfoLit",
    "tags": [
      "InfoLit"
    ],
    "updatedAt": "2026-07-03T00:00:00.000Z"
  },
  {
    "id": "in-glossary-317",
    "term": "IL概念316",
    "definition": "IL概念316说明",
    "category": "InfoLit",
    "tags": [
      "InfoLit"
    ],
    "updatedAt": "2026-07-03T00:00:00.000Z"
  },
  {
    "id": "in-glossary-318",
    "term": "IL概念317",
    "definition": "IL概念317说明",
    "category": "InfoLit",
    "tags": [
      "InfoLit"
    ],
    "updatedAt": "2026-07-03T00:00:00.000Z"
  },
  {
    "id": "in-glossary-319",
    "term": "IL概念318",
    "definition": "IL概念318说明",
    "category": "InfoLit",
    "tags": [
      "InfoLit"
    ],
    "updatedAt": "2026-07-03T00:00:00.000Z"
  },
  {
    "id": "in-glossary-320",
    "term": "IL概念319",
    "definition": "IL概念319说明",
    "category": "InfoLit",
    "tags": [
      "InfoLit"
    ],
    "updatedAt": "2026-07-03T00:00:00.000Z"
  },
  {
    "id": "in-glossary-321",
    "term": "IL概念320",
    "definition": "IL概念320说明",
    "category": "InfoLit",
    "tags": [
      "InfoLit"
    ],
    "updatedAt": "2026-07-03T00:00:00.000Z"
  },
  {
    "id": "in-glossary-322",
    "term": "IL概念321",
    "definition": "IL概念321说明",
    "category": "InfoLit",
    "tags": [
      "InfoLit"
    ],
    "updatedAt": "2026-07-03T00:00:00.000Z"
  },
  {
    "id": "in-glossary-323",
    "term": "IL概念322",
    "definition": "IL概念322说明",
    "category": "InfoLit",
    "tags": [
      "InfoLit"
    ],
    "updatedAt": "2026-07-03T00:00:00.000Z"
  },
  {
    "id": "in-glossary-324",
    "term": "IL概念323",
    "definition": "IL概念323说明",
    "category": "InfoLit",
    "tags": [
      "InfoLit"
    ],
    "updatedAt": "2026-07-03T00:00:00.000Z"
  },
  {
    "id": "in-glossary-325",
    "term": "IL概念324",
    "definition": "IL概念324说明",
    "category": "InfoLit",
    "tags": [
      "InfoLit"
    ],
    "updatedAt": "2026-07-03T00:00:00.000Z"
  },
  {
    "id": "in-glossary-326",
    "term": "IL概念325",
    "definition": "IL概念325说明",
    "category": "InfoLit",
    "tags": [
      "InfoLit"
    ],
    "updatedAt": "2026-07-03T00:00:00.000Z"
  },
  {
    "id": "in-glossary-327",
    "term": "IL概念326",
    "definition": "IL概念326说明",
    "category": "InfoLit",
    "tags": [
      "InfoLit"
    ],
    "updatedAt": "2026-07-03T00:00:00.000Z"
  },
  {
    "id": "in-glossary-328",
    "term": "IL概念327",
    "definition": "IL概念327说明",
    "category": "InfoLit",
    "tags": [
      "InfoLit"
    ],
    "updatedAt": "2026-07-03T00:00:00.000Z"
  },
  {
    "id": "in-glossary-329",
    "term": "IL概念328",
    "definition": "IL概念328说明",
    "category": "InfoLit",
    "tags": [
      "InfoLit"
    ],
    "updatedAt": "2026-07-03T00:00:00.000Z"
  },
  {
    "id": "in-glossary-330",
    "term": "IL概念329",
    "definition": "IL概念329说明",
    "category": "InfoLit",
    "tags": [
      "InfoLit"
    ],
    "updatedAt": "2026-07-03T00:00:00.000Z"
  },
  {
    "id": "in-glossary-331",
    "term": "IL概念330",
    "definition": "IL概念330说明",
    "category": "InfoLit",
    "tags": [
      "InfoLit"
    ],
    "updatedAt": "2026-07-03T00:00:00.000Z"
  },
  {
    "id": "in-glossary-332",
    "term": "IL概念331",
    "definition": "IL概念331说明",
    "category": "InfoLit",
    "tags": [
      "InfoLit"
    ],
    "updatedAt": "2026-07-03T00:00:00.000Z"
  },
  {
    "id": "in-glossary-333",
    "term": "IL概念332",
    "definition": "IL概念332说明",
    "category": "InfoLit",
    "tags": [
      "InfoLit"
    ],
    "updatedAt": "2026-07-03T00:00:00.000Z"
  },
  {
    "id": "in-glossary-334",
    "term": "IL概念333",
    "definition": "IL概念333说明",
    "category": "InfoLit",
    "tags": [
      "InfoLit"
    ],
    "updatedAt": "2026-07-03T00:00:00.000Z"
  },
  {
    "id": "in-glossary-335",
    "term": "IL概念334",
    "definition": "IL概念334说明",
    "category": "InfoLit",
    "tags": [
      "InfoLit"
    ],
    "updatedAt": "2026-07-03T00:00:00.000Z"
  },
  {
    "id": "in-glossary-336",
    "term": "IL概念335",
    "definition": "IL概念335说明",
    "category": "InfoLit",
    "tags": [
      "InfoLit"
    ],
    "updatedAt": "2026-07-03T00:00:00.000Z"
  },
  {
    "id": "in-glossary-337",
    "term": "IL概念336",
    "definition": "IL概念336说明",
    "category": "InfoLit",
    "tags": [
      "InfoLit"
    ],
    "updatedAt": "2026-07-03T00:00:00.000Z"
  },
  {
    "id": "in-glossary-338",
    "term": "IL概念337",
    "definition": "IL概念337说明",
    "category": "InfoLit",
    "tags": [
      "InfoLit"
    ],
    "updatedAt": "2026-07-03T00:00:00.000Z"
  },
  {
    "id": "in-glossary-339",
    "term": "IL概念338",
    "definition": "IL概念338说明",
    "category": "InfoLit",
    "tags": [
      "InfoLit"
    ],
    "updatedAt": "2026-07-03T00:00:00.000Z"
  },
  {
    "id": "in-glossary-340",
    "term": "IL概念339",
    "definition": "IL概念339说明",
    "category": "InfoLit",
    "tags": [
      "InfoLit"
    ],
    "updatedAt": "2026-07-03T00:00:00.000Z"
  },
  {
    "id": "in-glossary-341",
    "term": "IL概念340",
    "definition": "IL概念340说明",
    "category": "InfoLit",
    "tags": [
      "InfoLit"
    ],
    "updatedAt": "2026-07-03T00:00:00.000Z"
  },
  {
    "id": "in-glossary-342",
    "term": "IL概念341",
    "definition": "IL概念341说明",
    "category": "InfoLit",
    "tags": [
      "InfoLit"
    ],
    "updatedAt": "2026-07-03T00:00:00.000Z"
  },
  {
    "id": "in-glossary-343",
    "term": "IL概念342",
    "definition": "IL概念342说明",
    "category": "InfoLit",
    "tags": [
      "InfoLit"
    ],
    "updatedAt": "2026-07-03T00:00:00.000Z"
  },
  {
    "id": "in-glossary-344",
    "term": "IL概念343",
    "definition": "IL概念343说明",
    "category": "InfoLit",
    "tags": [
      "InfoLit"
    ],
    "updatedAt": "2026-07-03T00:00:00.000Z"
  },
  {
    "id": "in-glossary-345",
    "term": "IL概念344",
    "definition": "IL概念344说明",
    "category": "InfoLit",
    "tags": [
      "InfoLit"
    ],
    "updatedAt": "2026-07-03T00:00:00.000Z"
  },
  {
    "id": "in-glossary-346",
    "term": "IL概念345",
    "definition": "IL概念345说明",
    "category": "InfoLit",
    "tags": [
      "InfoLit"
    ],
    "updatedAt": "2026-07-03T00:00:00.000Z"
  },
  {
    "id": "in-glossary-347",
    "term": "IL概念346",
    "definition": "IL概念346说明",
    "category": "InfoLit",
    "tags": [
      "InfoLit"
    ],
    "updatedAt": "2026-07-03T00:00:00.000Z"
  },
  {
    "id": "in-glossary-348",
    "term": "IL概念347",
    "definition": "IL概念347说明",
    "category": "InfoLit",
    "tags": [
      "InfoLit"
    ],
    "updatedAt": "2026-07-03T00:00:00.000Z"
  },
  {
    "id": "in-glossary-349",
    "term": "IL概念348",
    "definition": "IL概念348说明",
    "category": "InfoLit",
    "tags": [
      "InfoLit"
    ],
    "updatedAt": "2026-07-03T00:00:00.000Z"
  },
  {
    "id": "in-glossary-350",
    "term": "IL概念349",
    "definition": "IL概念349说明",
    "category": "InfoLit",
    "tags": [
      "InfoLit"
    ],
    "updatedAt": "2026-07-03T00:00:00.000Z"
  },
  {
    "id": "in-glossary-351",
    "term": "IL概念350",
    "definition": "IL概念350说明",
    "category": "InfoLit",
    "tags": [
      "InfoLit"
    ],
    "updatedAt": "2026-07-03T00:00:00.000Z"
  },
  {
    "id": "in-glossary-352",
    "term": "IL概念351",
    "definition": "IL概念351说明",
    "category": "InfoLit",
    "tags": [
      "InfoLit"
    ],
    "updatedAt": "2026-07-03T00:00:00.000Z"
  },
  {
    "id": "in-glossary-353",
    "term": "IL概念352",
    "definition": "IL概念352说明",
    "category": "InfoLit",
    "tags": [
      "InfoLit"
    ],
    "updatedAt": "2026-07-03T00:00:00.000Z"
  },
  {
    "id": "in-glossary-354",
    "term": "IL概念353",
    "definition": "IL概念353说明",
    "category": "InfoLit",
    "tags": [
      "InfoLit"
    ],
    "updatedAt": "2026-07-03T00:00:00.000Z"
  },
  {
    "id": "in-glossary-355",
    "term": "IL概念354",
    "definition": "IL概念354说明",
    "category": "InfoLit",
    "tags": [
      "InfoLit"
    ],
    "updatedAt": "2026-07-03T00:00:00.000Z"
  },
  {
    "id": "in-glossary-356",
    "term": "IL概念355",
    "definition": "IL概念355说明",
    "category": "InfoLit",
    "tags": [
      "InfoLit"
    ],
    "updatedAt": "2026-07-03T00:00:00.000Z"
  },
  {
    "id": "in-glossary-357",
    "term": "IL概念356",
    "definition": "IL概念356说明",
    "category": "InfoLit",
    "tags": [
      "InfoLit"
    ],
    "updatedAt": "2026-07-03T00:00:00.000Z"
  },
  {
    "id": "in-glossary-358",
    "term": "IL概念357",
    "definition": "IL概念357说明",
    "category": "InfoLit",
    "tags": [
      "InfoLit"
    ],
    "updatedAt": "2026-07-03T00:00:00.000Z"
  },
  {
    "id": "in-glossary-359",
    "term": "IL概念358",
    "definition": "IL概念358说明",
    "category": "InfoLit",
    "tags": [
      "InfoLit"
    ],
    "updatedAt": "2026-07-03T00:00:00.000Z"
  },
  {
    "id": "in-glossary-360",
    "term": "IL概念359",
    "definition": "IL概念359说明",
    "category": "InfoLit",
    "tags": [
      "InfoLit"
    ],
    "updatedAt": "2026-07-03T00:00:00.000Z"
  }
]